openbb_forex/__init__.py
openbb_forex/forex_router.py
openbb_forex-0.1.0a4.dist-info/METADATA
openbb_forex-0.1.0a4.dist-info/WHEEL
openbb_forex-0.1.0a4.dist-info/entry_points.txt
openbb_forex-0.1.0a4.dist-info/RECORD
